neurofhir/__init__.py
neurofhir/causal_edge_miner.py
neurofhir/hyperbolic_encoder.py
neurofhir/temporal_builder.py
neurofhir-0.1.4.dist-info/licenses/LICENSE
neurofhir-0.1.4.dist-info/METADATA
neurofhir-0.1.4.dist-info/WHEEL
neurofhir-0.1.4.dist-info/top_level.txt
neurofhir-0.1.4.dist-info/RECORD
