Metadata-Version: 2.4
Name: neurofhir
Version: 0.1.4
Summary: Geometric Deep Learning for FHIR: Temporal, Hyperbolic, and Causal Graph Tensors
Author-email: ATIL İHSAN YALI <nano.carbay@gmail.com>
License: AGPL-3.0-or-later
Project-URL: Homepage, https://github.com/nanobiolog/FHIR-to-Tensor
Project-URL: Bug Tracker, https://github.com/nanobiolog/FHIR-to-Tensor/issues
Keywords: fhir,graph-neural-networks,geometric-deep-learning,healthcare,temporal-graphs
Classifier: Development Status :: 3 - Alpha
Classifier: Intended Audience :: Healthcare Industry
Classifier: Intended Audience :: Science/Research
Classifier: Programming Language :: Python :: 3
Classifier: Topic :: Scientific/Engineering :: Artificial Intelligence
Classifier: Topic :: Scientific/Engineering :: Medical Science Apps.
Requires-Python: >=3.9
License-File: LICENSE
Requires-Dist: polars>=0.19.0
Requires-Dist: torch>=2.0.0
Requires-Dist: networkx>=3.0
Provides-Extra: full
Requires-Dist: torch_geometric>=2.4.0; extra == "full"
Requires-Dist: torch_geometric_temporal>=0.54.0; extra == "full"
Provides-Extra: dev
Requires-Dist: pytest>=7.0.0; extra == "dev"
Requires-Dist: black>=23.0.0; extra == "dev"
Requires-Dist: twine>=4.0.0; extra == "dev"
Requires-Dist: build>=0.10.0; extra == "dev"
Dynamic: license-file
